conventional_pre_commit/__init__.py
conventional_pre_commit/format.py
conventional_pre_commit/hook.py
conventional_pre_commit/output.py
conventional_pre_commit-4.3.0.dist-info/licenses/LICENSE
conventional_pre_commit-4.3.0.dist-info/METADATA
conventional_pre_commit-4.3.0.dist-info/WHEEL
conventional_pre_commit-4.3.0.dist-info/entry_points.txt
conventional_pre_commit-4.3.0.dist-info/top_level.txt
conventional_pre_commit-4.3.0.dist-info/RECORD
