Metadata-Version: 2.4
Name: conventional_pre_commit
Version: 4.3.0
Summary: A pre-commit hook that checks commit messages for Conventional Commits formatting.
Author-email: Compiler LLC <dev@compiler.la>
License:                                  Apache License
Project-URL: code, https://github.com/compilerla/conventional-pre-commit
Project-URL: tracker, https://github.com/compilerla/conventional-pre-commit/issues
Keywords: git,pre-commit,conventional-commits
Classifier: Programming Language :: Python :: 3 :: Only
Requires-Python: >=3.8
License-File: LICENSE
Provides-Extra: dev
Requires-Dist: black; extra == "dev"
Requires-Dist: build; extra == "dev"
Requires-Dist: coverage; extra == "dev"
Requires-Dist: flake8; extra == "dev"
Requires-Dist: pre-commit; extra == "dev"
Requires-Dist: pytest; extra == "dev"
Requires-Dist: setuptools_scm; extra == "dev"
Dynamic: license-file
